insteonterminal/__init__.py
insteonterminal/__main__.py
insteonterminal-0.0.2.dist-info/LICENSE
insteonterminal-0.0.2.dist-info/METADATA
insteonterminal-0.0.2.dist-info/WHEEL
insteonterminal-0.0.2.dist-info/entry_points.txt
insteonterminal-0.0.2.dist-info/top_level.txt
insteonterminal-0.0.2.dist-info/RECORD
